{"number": "11", "course": "CIE IGCSE PHYSICS", "year": "2004", "paper": "Paper 1", "month": "June", "text": "A boy and a girl run up a hill in the same time.\n\n \n\nboy weighs 600 N girl weighs 500N\n\nThe boy weighs more than the girl.\n\nWhich statement is true about the power produced?\n\nA\n\nB\nCc\nD\n\nThe boy produces more power.\nThe girl produces more power.\nThey both produce the same power.\n\nIt is impossible to tell who produces more power.\n\f", "topic": "2.2 Thermal properties and temperature", "answer": "A"}